keysec/__init__.py
keysec/__main__.py
keysec/iokeys.py
keysec/keysec.py
keysec/version.py
keysec/actions/__init__.py
keysec/actions/conv.py
keysec/actions/edit.py
keysec/actions/gen.py
keysec/actions/info.py
keysec/parsers/__init__.py
keysec/parsers/args.py
keysec/parsers/conv.py
keysec/parsers/edit.py
keysec/parsers/gen.py
keysec/parsers/info.py
keysec/parsers/top.py
keysec/parsers/utils.py
keysec-1.4.0.dist-info/LICENSE
keysec-1.4.0.dist-info/METADATA
keysec-1.4.0.dist-info/WHEEL
keysec-1.4.0.dist-info/entry_points.txt
keysec-1.4.0.dist-info/top_level.txt
keysec-1.4.0.dist-info/zip-safe
keysec-1.4.0.dist-info/RECORD
