Metadata-Version: 2.1
Name: keysec
Version: 1.4.0
Summary: With this program you will be able to generate OpenSSL and OpenSSH keys (RSA, Ed25519) and carry out transformations between both formats.
Home-page: https://github.com/fernandoenzo/keysec
Download-URL: https://github.com/fernandoenzo/keysec/releases
Author: Fernando Enzo Guarini
Author-email: fernandoenzo@gmail.com
Maintainer: 
Maintainer-email: 
License: GPLv3+
Keywords: openssl ssl openssh ssh key private public rsa ed25519 elliptic curve cyrptography convert transform keys format pem pkcs
Platform: any
Classifier: Development Status :: 5 - Production/Stable
Classifier: Environment :: Console
Classifier: Intended Audience :: End Users/Desktop
Classifier: License :: OSI Approved :: GNU General Public License v3 or later (GPLv3+)
Classifier: Natural Language :: English
Classifier: Operating System :: POSIX :: Linux
Classifier: Programming Language :: Python :: 3.9
Classifier: Programming Language :: Python :: 3.10
Classifier: Programming Language :: Python :: 3.11
Classifier: Topic :: Security
Classifier: Topic :: Security :: Cryptography
Classifier: Topic :: Communications
Classifier: Topic :: Internet
Classifier: Topic :: System :: Networking
Classifier: Topic :: Utilities
Requires-Python: >=3.9
License-File: LICENSE
Requires-Dist: bcrypt (==4.0.1)
Requires-Dist: cryptography (==40.0.1)
